<?xml version="1.0" encoding="UTF-8" standalone="no"?>
<!DOCTYPE EFG PUBLIC "EFG" "eventtree.dtd">
<EFG id="root" session_app="ApplicationInfo{40511a68 org.wordpress.android}" session_date_time="Tue Jul 29 19:00:09 GMT+00:00 2014">
    <EVENT desc="Read" id="e11" type="click" value="" widget_id="2131165263" widget_name="" widget_type="android.widget.LinearLayout">
        <EVENT desc="" id="e17" type="openMenu" value="" widget_id="-1" widget_name="" widget_type="null">
            <EVENT desc="" id="e23" type="openMenu" value="" widget_id="-1" widget_name="" widget_type="null">
                <EVENT desc="" id="e28" type="changeOrientation" value="" widget_id="-1" widget_name="" widget_type="null">
                    <EVENT desc="" id="e29" type="longClick" value="" widget_id="2131165329" widget_name="" widget_type="android.webkit.WebView">
                        <EVENT desc="" id="e33" type="longClick" value="" widget_id="2131165329" widget_name="" widget_type="android.webkit.WebView">
                            <EVENT desc="" id="e39" type="openMenu" value="" widget_id="-1" widget_name="" widget_type="null">
                                <EVENT desc="" id="e44" type="back" value="" widget_id="-1" widget_name="" widget_type="null">
                                    <EVENT desc="" id="e48" type="back" value="" widget_id="-1" widget_name="" widget_type="null">
                                        <EVENT desc="Settings" id="e61" type="click" value="" widget_id="2131165262" widget_name="" widget_type="android.widget.LinearLayout">
                                            <EVENT desc="800" id="e75" type="selectSpinnerItem" value="9" widget_id="2131165348" widget_name="" widget_type="android.widget.Spinner">
                                                <EVENT desc="700" id="e93" type="selectSpinnerItem" value="8" widget_id="2131165348" widget_name="" widget_type="android.widget.Spinner">
                                                    <EVENT desc="300" id="e108" type="selectSpinnerItem" value="4" widget_id="2131165348" widget_name="" widget_type="android.widget.Spinner">
                                                        <EVENT desc="" id="e142" type="changeOrientation" value="" widget_id="-1" widget_name="" widget_type="null">
                                                            <EVENT desc="" id="e158" type="click" value="" widget_id="2131165200" widget_name="" widget_type="android.widget.ImageButton">
                                                                <EVENT desc="Settings" id="e186" type="click" value="" widget_id="2131165262" widget_name="" widget_type="android.widget.LinearLayout">
                                                                    <EVENT desc="Save" id="e205" type="click" value="" widget_id="2131165219" widget_name="Save" widget_type="android.widget.Button">
                                                                        <EVENT desc="" id="e211" type="click" value="" widget_id="2131165200" widget_name="" widget_type="android.widget.ImageButton">
                                                                            <EVENT desc="" id="e227" type="click" value="" widget_id="2131165200" widget_name="" widget_type="android.widget.ImageButton">
                                                                                <EVENT desc="Comments" id="e241" type="click" value="" widget_id="2131165258" widget_name="" widget_type="android.widget.LinearLayout">
                                                                                    <EVENT desc="" id="e250" type="openMenu" value="" widget_id="-1" widget_name="" widget_type="null">
                                                                                        <EVENT desc="OK" id="e252" type="click" value="" widget_id="16908313" widget_name="OK" widget_type="android.widget.Button">
                                                                                            <EVENT desc="" id="e257" type="click" value="" widget_id="2131165201" widget_name="" widget_type="android.widget.Button">
                                                                                                <EVENT desc="" id="e262" type="back" value="" widget_id="-1" widget_name="" widget_type="null">
                                                                                                    <EVENT desc="" id="e266" type="click" value="" widget_id="2131165201" widget_name="" widget_type="android.widget.Button">
                                                                                                        <EVENT desc="" id="e272" type="openMenu" value="" widget_id="-1" widget_name="" widget_type="null">
                                                                                                            <EVENT desc="OK" id="e274" type="click" value="" widget_id="16908313" widget_name="OK" widget_type="android.widget.Button">
                                                                                                                <EVENT desc="" id="e279" type="click" value="" widget_id="2131165201" widget_name="" widget_type="android.widget.Button">
                                                                                                                    <EVENT desc="OK" id="e283" type="click" value="" widget_id="16908313" widget_name="OK" widget_type="android.widget.Button">
                                                                                                                        <EVENT desc="" id="e289" type="back" value="" widget_id="-1" widget_name="" widget_type="null">
                                                                                                                            <EVENT desc="Pages" id="e300" type="click" value="" widget_id="2131165257" widget_name="" widget_type="android.widget.LinearLayout">
                                                                                                                                <EVENT desc="" id="e309" type="back" value="" widget_id="-1" widget_name="" widget_type="null">
                                                                                                                                    <EVENT desc="" id="e315" type="openMenu" value="" widget_id="-1" widget_name="" widget_type="null">
                                                                                                                                        <EVENT desc="New Page" id="e317" type="click" value="" widget_id="16908310" widget_name="New Page" widget_type="com.android.internal.view.menu.IconMenuItemView">
                                                                                                                                            <EVENT desc="" id="e326" type="changeOrientation" value="" widget_id="-1" widget_name="" widget_type="null">
                                                                                                                                                <EVENT desc="Edit" id="e328" type="click" value="" widget_id="2131165283" widget_name="Edit" widget_type="android.widget.Button">
                                                                                                                                                    <EVENT desc="" id="e338" type="click" value="" widget_id="16908796" widget_name="" widget_type="android.widget.NumberPickerButton">
                                                                                                                                                        <EVENT desc="28" id="e351" type="focus" value="" widget_id="16908795" widget_name="" widget_type="android.widget.EditText">
                                                                                                                                                            <EVENT desc="2014" id="e368" type="focus" value="" widget_id="16908795" widget_name="" widget_type="android.widget.EditText">
                                                                                                                                                                <EVENT desc="" id="e381" type="click" value="" widget_id="16908794" widget_name="" widget_type="android.widget.NumberPickerButton">
                                                                                                                                                                    <EVENT desc="28" id="e393" type="focus" value="" widget_id="16908795" widget_name="" widget_type="android.widget.EditText">
                                                                                                                                                                        <EVENT desc="" id="e406" type="click" value="" widget_id="16908794" widget_name="" widget_type="android.widget.NumberPickerButton">
                                                                                                                                                                            <EVENT desc="" id="e423" type="click" value="" widget_id="16908794" widget_name="" widget_type="android.widget.NumberPickerButton">
                                                                                                                                                                                <EVENT desc="" id="e434" type="click" value="" widget_id="16908794" widget_name="" widget_type="android.widget.NumberPickerButton">
                                                                                                                                                                                    <EVENT desc="Jul" id="e446" type="focus" value="" widget_id="16908795" widget_name="" widget_type="android.widget.EditText">
                                                                                                                                                                                        <EVENT desc="" id="e470" type="back" value="" widget_id="-1" widget_name="" widget_type="null">
                                                                                                                                                                                            <EVENT desc="" id="e478" type="click" value="" widget_id="16908796" widget_name="" widget_type="android.widget.NumberPickerButton">
                                                                                                                                                                                                <EVENT desc="" id="e493" type="click" value="" widget_id="16908794" widget_name="" widget_type="android.widget.NumberPickerButton">
                                                                                                                                                                                                    <EVENT desc="Cancel" id="e511" type="click" value="" widget_id="16908314" widget_name="Cancel" widget_type="android.widget.Button">
                                                                                                                                                                                                        <EVENT desc="" id="e520" type="changeOrientation" value="" widget_id="-1" widget_name="" widget_type="null">
                                                                                                                                                                                                            <EVENT desc="" id="e526" type="changeOrientation" value="" widget_id="-1" widget_name="" widget_type="null">
                                                                                                                                                                                                                <EVENT desc="" id="e527" type="focus" value="" widget_id="2131165265" widget_name="Content" widget_type="org.wordpress.android.util.WPEditText">
                                                                                                                                                                                                                    <EVENT desc="" id="e542" type="back" value="" widget_id="-1" widget_name="" widget_type="null">
                                                                                                                                                                                                                        <EVENT desc="Edit" id="e546" type="click" value="" widget_id="2131165283" widget_name="Edit" widget_type="android.widget.Button">
                                                                                                                                                                                                                            <EVENT desc="" id="e556" type="click" value="" widget_id="16908796" widget_name="" widget_type="android.widget.NumberPickerButton">
                                                                                                                                                                                                                                <EVENT desc="Cancel" id="e575" type="click" value="" widget_id="16908314" widget_name="Cancel" widget_type="android.widget.Button">
                                                                                                                                                                                                                                    <EVENT desc="Publish" id="e581" type="click" value="" widget_id="2131165287" widget_name="Publish" widget_type="android.widget.Button">
                                                                                                                                                                                                                                        <EVENT desc="" id="e588" type="changeOrientation" value="" widget_id="-1" widget_name="" widget_type="null">
                                                                                                                                                                                                                                            <EVENT desc="" id="e592" type="changeOrientation" value="" widget_id="-1" widget_name="" widget_type="null">
                                                                                                                                                                                                                                                <EVENT desc="OK" id="e593" type="click" value="" widget_id="16908313" widget_name="OK" widget_type="android.widget.Button">
                                                                                                                                                                                                                                                    <EVENT desc="Edit" id="e598" type="click" value="" widget_id="2131165283" widget_name="Edit" widget_type="android.widget.Button">
                                                                                                                                                                                                                                                        <EVENT desc="" id="e609" type="click" value="" widget_id="16908794" widget_name="" widget_type="android.widget.NumberPickerButton">
                                                                                                                                                                                                                                                            <EVENT desc="" id="e620" type="click" value="" widget_id="16908794" widget_name="" widget_type="android.widget.NumberPickerButton">
                                                                                                                                                                                                                                                                <EVENT desc="" id="e637" type="click" value="" widget_id="16908794" widget_name="" widget_type="android.widget.NumberPickerButton">
                                                                                                                                                                                                                                                                    <EVENT desc="" id="e657" type="openMenu" value="" widget_id="-1" widget_name="" widget_type="null">
                                                                                                                                                                                                                                                                        <EVENT desc="29" id="e663" type="focus" value="" widget_id="16908795" widget_name="" widget_type="android.widget.EditText">
                                                                                                                                                                                                                                                                            <EVENT desc="" id="e673" type="click" value="" widget_id="16908794" widget_name="" widget_type="android.widget.NumberPickerButton">
                                                                                                                                                                                                                                                                                <EVENT desc="Aug" id="e688" type="focus" value="" widget_id="16908795" widget_name="" widget_type="android.widget.EditText">
                                                                                                                                                                                                                                                                                    <EVENT desc="" id="e714" type="changeOrientation" value="" widget_id="-1" widget_name="" widget_type="null">
                                                                                                                                                                                                                                                                                        <EVENT desc="" id="e720" type="click" value="" widget_id="16908796" widget_name="" widget_type="android.widget.NumberPickerButton">
                                                                                                                                                                                                                                                                                            <EVENT desc="2019" id="e736" type="focus" value="" widget_id="16908795" widget_name="" widget_type="android.widget.EditText">
                                                                                                                                                                                                                                                                                                <EVENT desc="" id="e748" type="click" value="" widget_id="16908796" widget_name="" widget_type="android.widget.NumberPickerButton"/>
                                                                                                                                                                                                                                                                                            </EVENT>
                                                                                                                                                                                                                                                                                        </EVENT>
                                                                                                                                                                                                                                                                                    </EVENT>
                                                                                                                                                                                                                                                                                </EVENT>
                                                                                                                                                                                                                                                                            </EVENT>
                                                                                                                                                                                                                                                                        </EVENT>
                                                                                                                                                                                                                                                                    </EVENT>
                                                                                                                                                                                                                                                                </EVENT>
                                                                                                                                                                                                                                                            </EVENT>
                                                                                                                                                                                                                                                        </EVENT>
                                                                                                                                                                                                                                                    </EVENT>
                                                                                                                                                                                                                                                </EVENT>
                                                                                                                                                                                                                                            </EVENT>
                                                                                                                                                                                                                                        </EVENT>
                                                                                                                                                                                                                                    </EVENT>
                                                                                                                                                                                                                                </EVENT>
                                                                                                                                                                                                                            </EVENT>
                                                                                                                                                                                                                        </EVENT>
                                                                                                                                                                                                                    </EVENT>
                                                                                                                                                                                                                </EVENT>
                                                                                                                                                                                                            </EVENT>
                                                                                                                                                                                                        </EVENT>
                                                                                                                                                                                                    </EVENT>
                                                                                                                                                                                                </EVENT>
                                                                                                                                                                                            </EVENT>
                                                                                                                                                                                        </EVENT>
                                                                                                                                                                                    </EVENT>
                                                                                                                                                                                </EVENT>
                                                                                                                                                                            </EVENT>
                                                                                                                                                                        </EVENT>
                                                                                                                                                                    </EVENT>
                                                                                                                                                                </EVENT>
                                                                                                                                                            </EVENT>
                                                                                                                                                        </EVENT>
                                                                                                                                                    </EVENT>
                                                                                                                                                </EVENT>
                                                                                                                                            </EVENT>
                                                                                                                                        </EVENT>
                                                                                                                                    </EVENT>
                                                                                                                                </EVENT>
                                                                                                                            </EVENT>
                                                                                                                        </EVENT>
                                                                                                                    </EVENT>
                                                                                                                </EVENT>
                                                                                                            </EVENT>
                                                                                                        </EVENT>
                                                                                                    </EVENT>
                                                                                                </EVENT>
                                                                                            </EVENT>
                                                                                        </EVENT>
                                                                                    </EVENT>
                                                                                </EVENT>
                                                                            </EVENT>
                                                                        </EVENT>
                                                                    </EVENT>
                                                                </EVENT>
                                                            </EVENT>
                                                        </EVENT>
                                                    </EVENT>
                                                </EVENT>
                                            </EVENT>
                                        </EVENT>
                                    </EVENT>
                                </EVENT>
                            </EVENT>
                        </EVENT>
                    </EVENT>
                </EVENT>
            </EVENT>
        </EVENT>
    </EVENT>
    <EVENT desc="" id="e757" type="openMenu" value="" widget_id="-1" widget_name="" widget_type="null"/>
    <EVENT desc="" id="e760" type="click" value="" widget_id="2131165201" widget_name="" widget_type="android.widget.Button">
        <EVENT desc="Read" id="e785" type="click" value="" widget_id="2131165263" widget_name="" widget_type="android.widget.LinearLayout">
            <EVENT desc="" id="e793" type="changeOrientation" value="" widget_id="-1" widget_name="" widget_type="null">
                <EVENT desc="" id="e796" type="openMenu" value="" widget_id="-1" widget_name="" widget_type="null">
                    <EVENT desc="Home" id="e798" type="click" value="" widget_id="16908310" widget_name="Home" widget_type="com.android.internal.view.menu.IconMenuItemView">
                        <EVENT desc="Read" id="e815" type="click" value="" widget_id="2131165263" widget_name="" widget_type="android.widget.LinearLayout">
                            <EVENT desc="" id="e823" type="changeOrientation" value="" widget_id="-1" widget_name="" widget_type="null">
                                <EVENT desc="" id="e825" type="back" value="" widget_id="-1" widget_name="" widget_type="null">
                                    <EVENT desc="Read" id="e839" type="click" value="" widget_id="2131165263" widget_name="" widget_type="android.widget.LinearLayout">
                                        <EVENT desc="" id="e847" type="changeOrientation" value="" widget_id="-1" widget_name="" widget_type="null">
                                            <EVENT desc="" id="e851" type="changeOrientation" value="" widget_id="-1" widget_name="" widget_type="null">
                                                <EVENT desc="" id="e854" type="openMenu" value="" widget_id="-1" widget_name="" widget_type="null">
                                                    <EVENT desc="" id="e860" type="openMenu" value="" widget_id="-1" widget_name="" widget_type="null">
                                                        <EVENT desc="" id="e862" type="longClick" value="" widget_id="2131165329" widget_name="" widget_type="android.webkit.WebView">
                                                            <EVENT desc="" id="e867" type="click" value="" widget_id="-1" widget_name="Email or Username&#10;&#9;&#9;" widget_type="android.webkit.WebTextView">
                                                                <EVENT desc="" id="e872" type="click" value="" widget_id="-1" widget_name="Email or Username&#10;&#9;&#9;" widget_type="android.webkit.WebTextView">
                                                                    <EVENT desc="" id="e876" type="longClick" value="" widget_id="2131165329" widget_name="" widget_type="android.webkit.WebView">
                                                                        <EVENT desc="" id="e882" type="click" value="" widget_id="-1" widget_name="Email or Username&#10;&#9;&#9;" widget_type="android.webkit.WebTextView">
                                                                            <EVENT desc="" id="e889" type="openMenu" value="" widget_id="-1" widget_name="" widget_type="null">
                                                                                <EVENT desc="" id="e896" type="changeOrientation" value="" widget_id="-1" widget_name="" widget_type="null">
                                                                                    <EVENT desc="" id="e900" type="back" value="" widget_id="-1" widget_name="" widget_type="null">
                                                                                        <EVENT desc="" id="e906" type="openMenu" value="" widget_id="-1" widget_name="" widget_type="null">
                                                                                            <EVENT desc="" id="e912" type="openMenu" value="" widget_id="-1" widget_name="" widget_type="null">
                                                                                                <EVENT desc="" id="e916" type="back" value="" widget_id="-1" widget_name="" widget_type="null">
                                                                                                    <EVENT desc="New Post" id="e921" type="click" value="" widget_id="2131165204" widget_name="" widget_type="android.widget.LinearLayout">
                                                                                                        <EVENT desc="OK" id="e935" type="click" value="" widget_id="16908313" widget_name="OK" widget_type="android.widget.Button">
                                                                                                            <EVENT desc="" id="e942" type="openMenu" value="" widget_id="-1" widget_name="" widget_type="null">
                                                                                                                <EVENT desc="" id="e945" type="back" value="" widget_id="-1" widget_name="" widget_type="null">
                                                                                                                    <EVENT desc="" id="e948" type="click" value="" widget_id="2131165200" widget_name="" widget_type="android.widget.ImageButton"/>
                                                                                                                </EVENT>
                                                                                                            </EVENT>
                                                                                                        </EVENT>
                                                                                                    </EVENT>
                                                                                                </EVENT>
                                                                                            </EVENT>
                                                                                        </EVENT>
                                                                                    </EVENT>
                                                                                </EVENT>
                                                                            </EVENT>
                                                                        </EVENT>
                                                                    </EVENT>
                                                                </EVENT>
                                                            </EVENT>
                                                        </EVENT>
                                                    </EVENT>
                                                </EVENT>
                                            </EVENT>
                                        </EVENT>
                                    </EVENT>
                                </EVENT>
                            </EVENT>
                        </EVENT>
                    </EVENT>
                </EVENT>
            </EVENT>
        </EVENT>
    </EVENT>
</EFG>

